uib_inf100_graphics/__init__.py
uib_inf100_graphics/version.py
uib_inf100_graphics/event_app/__init__.py
uib_inf100_graphics/event_app/types.py
uib_inf100_graphics/event_app/uib_inf100_graphics.py
uib_inf100_graphics/helpers/__init__.py
uib_inf100_graphics/helpers/image.py
uib_inf100_graphics/helpers/logger.py
uib_inf100_graphics/helpers/text.py
uib_inf100_graphics/simple/Configuration.py
uib_inf100_graphics/simple/RecordingCanvas.py
uib_inf100_graphics/simple/SimplifiedFrame.py
uib_inf100_graphics/simple/__init__.py
uib_inf100_graphics/simple/globals.py
uib_inf100_graphics-0.4.0.dist-info/METADATA
uib_inf100_graphics-0.4.0.dist-info/WHEEL
uib_inf100_graphics-0.4.0.dist-info/top_level.txt
uib_inf100_graphics-0.4.0.dist-info/RECORD
