Metadata-Version: 2.1
Name: uib-inf100-graphics
Version: 0.4.0
Summary: A simple graphics library for INF100 at the University of Bergen.
Author-email: Torstein Strømme <torstein.stromme@uib.no>
Project-URL: Homepage, https://github.com/torsteins/uib_inf100_graphics
Project-URL: Issues, https://github.com/torsteins/uib_inf100_graphics/issues
Classifier: Programming Language :: Python :: 3 :: Only
Classifier: Programming Language :: Python :: 3.10
Classifier: Programming Language :: Python :: 3.11
Classifier: Operating System :: OS Independent
Classifier: Intended Audience :: Education
Classifier: Topic :: Education
Classifier: Topic :: Software Development :: Libraries :: Tcl Extensions
Requires-Python: >=3.10
Requires-Dist: Pillow >=9.2.0
Requires-Dist: requests >=2.28.0
